CreateData/__init__.py
CreateData/create_data.py
CreateData-1.0.1.dist-info/LICENSE.txt
CreateData-1.0.1.dist-info/METADATA
CreateData-1.0.1.dist-info/WHEEL
CreateData-1.0.1.dist-info/top_level.txt
CreateData-1.0.1.dist-info/RECORD
