Metadata-Version: 2.1
Name: CreateData
Version: 1.0.1
Summary: Easy data generation
Home-page: https://github.com/dwenlvov/
Author: denis_lvov
Author-email: dwenlvov@gmail.com
Project-URL: Documentation, https://github.com/dwenlvov/CreateData/
Keywords: pandas
Classifier: Programming Language :: Python :: 3.11
Classifier: License :: OSI Approved :: MIT License
Requires-Python: >=3.11
License-File: LICENSE.txt
